README.md
setup.cfg
setup.py
Prediction_Utils/__init__.py
Prediction_Utils/main.py
Prediction_Utils.egg-info/PKG-INFO
Prediction_Utils.egg-info/SOURCES.txt
Prediction_Utils.egg-info/dependency_links.txt
Prediction_Utils.egg-info/requires.txt
Prediction_Utils.egg-info/top_level.txt
Prediction_Utils/Classification/__init__.py
Prediction_Utils/Classification/_use_lasso.py
Prediction_Utils/Classification/_use_rf.py
Prediction_Utils/Classification/_use_svc.py
Prediction_Utils/Regression/__init__.py
Prediction_Utils/Regression/_use_lasso.py
Prediction_Utils/Regression/_use_rf.py
Prediction_Utils/Regression/_use_svr.py